[
  {
    "tesKey": "reading",
    "tesNama": "Pemahaman Bacaan",
    "pesertaNama": "Admin Dimz",
    "skor": 5,
    "totalSoal": 20,
    "waktuDipakai": 69,
    "timestamp": "2026-05-26T10:54:27.824Z"
  },
  {
    "tesKey": "iq",
    "tesNama": "Tes IQ",
    "pesertaNama": "Admin Eji",
    "skor": 19,
    "totalSoal": 25,
    "waktuDipakai": 581,
    "timestamp": "2026-05-26T11:30:30.874Z"
  },
  {
    "tesKey": "iq",
    "tesNama": "Tes IQ",
    "pesertaNama": "ENGGAR",
    "skor": 13,
    "totalSoal": 25,
    "waktuDipakai": 396,
    "timestamp": "2026-05-26T11:56:23.158Z"
  },
  {
    "tesKey": "iq",
    "tesNama": "Tes IQ",
    "pesertaNama": "Patur Rahman",
    "skor": 23,
    "totalSoal": 25,
    "waktuDipakai": 1407,
    "timestamp": "2026-05-26T12:47:43.822Z"
  }
]